TracknTrace/Prototype_Amini.metadata
TracknTrace/Prototype_Amini.xlsx
TracknTrace/__init__.py
TracknTrace/analysis.py
TracknTrace/uurgeg_290_2011-2020.txt
TracknTrace/uurgeg_290_2021-2030.txt
TracknTrace/wrapper.py
TracknTrace/categorizer/__init__.py
TracknTrace/categorizer/categorizer.py
TracknTrace/preprocessor/__init__.py
TracknTrace/preprocessor/preProcessor.py
trackntrace-0.1.0.dist-info/licenses/LICENSE
trackntrace-0.1.0.dist-info/METADATA
trackntrace-0.1.0.dist-info/WHEEL
trackntrace-0.1.0.dist-info/entry_points.txt
trackntrace-0.1.0.dist-info/top_level.txt
trackntrace-0.1.0.dist-info/RECORD
