Metadata-Version: 2.4
Name: TracknTrace
Version: 0.1.0
Summary: Track building performance and Trace errors
Home-page: https://github.com/Kwabratseur/TracknTrace
Author: Jeroen van 't Ende
Author-email: jeroen.vantende@outlook.com
License: MIT
Keywords: Track Trace building performance errors gap analysis DSMR KNMI blame
Classifier: Development Status :: 3 - Alpha
Classifier: License :: OSI Approved :: MIT License
Classifier: Programming Language :: Python :: 3.11
Classifier: Programming Language :: Python :: 3.12
Classifier: Programming Language :: Python :: 3.13
Classifier: Topic :: Scientific/Engineering :: Atmospheric Science
Classifier: Intended Audience :: Science/Research
Classifier: Intended Audience :: Education
License-File: LICENSE
Requires-Dist: pandas
Requires-Dist: numpy
Requires-Dist: markdown
Requires-Dist: matplotlib
Requires-Dist: pillow
Requires-Dist: pytexit
Requires-Dist: seaborn
Requires-Dist: scikit-learn
Requires-Dist: mufit
Requires-Dist: openpyxl
Requires-Dist: tabulate
Requires-Dist: latex
Dynamic: author
Dynamic: author-email
Dynamic: classifier
Dynamic: description
Dynamic: description-content-type
Dynamic: home-page
Dynamic: keywords
Dynamic: license
Dynamic: license-file
Dynamic: requires-dist
Dynamic: summary
